odoo/addons/account_move_line_drilldown/README.rst
odoo/addons/account_move_line_drilldown/__init__.py
odoo/addons/account_move_line_drilldown/__manifest__.py
odoo/addons/account_move_line_drilldown/hooks.py
odoo/addons/account_move_line_drilldown/i18n/account_move_line_drilldown.pot
odoo/addons/account_move_line_drilldown/models/__init__.py
odoo/addons/account_move_line_drilldown/models/account_account.py
odoo/addons/account_move_line_drilldown/models/account_group.py
odoo/addons/account_move_line_drilldown/models/account_move_line.py
odoo/addons/account_move_line_drilldown/readme/CONFIGURE.rst
odoo/addons/account_move_line_drilldown/readme/CONTRIBUTORS.readme
odoo/addons/account_move_line_drilldown/readme/DESCRIPTION.rst
odoo/addons/account_move_line_drilldown/readme/INSTALL.rst
odoo/addons/account_move_line_drilldown/readme/USAGE.rst
odoo/addons/account_move_line_drilldown/static/description/drilldown_pivot.png
odoo/addons/account_move_line_drilldown/static/description/drilldown_tree.png
odoo/addons/account_move_line_drilldown/static/description/icon.png
odoo/addons/account_move_line_drilldown/static/description/index.html
odoo/addons/account_move_line_drilldown/tests/__init__.py
odoo/addons/account_move_line_drilldown/tests/test_account_move_line_drilldown.py
odoo/addons/account_move_line_drilldown/views/account_move_line_view.xml
odoo12_addon_account_move_line_drilldown-12.0.1.0.0.99.dev4.dist-info/METADATA
odoo12_addon_account_move_line_drilldown-12.0.1.0.0.99.dev4.dist-info/WHEEL
odoo12_addon_account_move_line_drilldown-12.0.1.0.0.99.dev4.dist-info/top_level.txt
odoo12_addon_account_move_line_drilldown-12.0.1.0.0.99.dev4.dist-info/RECORD
